LICENSE.txt
MANIFEST.in
README.rst
setup.cfg
setup.py
shopify_stream_sdk.egg-info/PKG-INFO
shopify_stream_sdk.egg-info/SOURCES.txt
shopify_stream_sdk.egg-info/dependency_links.txt
shopify_stream_sdk.egg-info/top_level.txt
shopifystream/__init__.py
shopifystream/wrapper.py