Metadata-Version: 1.1
Name: shopify-stream-sdk
Version: 0.0.1
Summary: Shopify Stream SDK
Home-page: https://github.com/kfichter/shopify-stream-sdk
Author: Kelvin Fichter
Author-email: UNKNOWN
License: MIT
Keywords: shopify websockets development
Platform: UNKNOWN
Classifier: Development Status :: 3 - Alpha
Classifier: Intended Audience :: Developers
Classifier: Topic :: Software Development :: Libraries :: Python Modules
Classifier: License :: OSI Approved :: MIT License
Classifier: Programming Language :: Python :: 3.5
